pycocotools/__init__.py
pycocotools/_mask.cp38-win_amd64.pyd
pycocotools/coco.py
pycocotools/cocoeval.py
pycocotools/mask.py
pycocotools_windows-2.0.0.2.dist-info/METADATA
pycocotools_windows-2.0.0.2.dist-info/WHEEL
pycocotools_windows-2.0.0.2.dist-info/top_level.txt
pycocotools_windows-2.0.0.2.dist-info/RECORD
